json_tools2/__init__.py
json_tools2/flat_json.py
json_tools2/schema.py
json_tools2/spark.py
json_tools2/transform.py
json_tools2/util.py
json_tools2-0.0.11.dist-info/LICENSE
json_tools2-0.0.11.dist-info/METADATA
json_tools2-0.0.11.dist-info/WHEEL
json_tools2-0.0.11.dist-info/top_level.txt
json_tools2-0.0.11.dist-info/RECORD
