Metadata-Version: 2.1
Name: json-tools2
Version: 0.0.11
Summary: JSON Tools Library
Home-page: https://github.com/stonezhong/json_tools2
Author: Stone Zhong
Author-email: stonezhong@hotmail.com
License: MIT
Classifier: License :: OSI Approved :: MIT License
Classifier: Programming Language :: Python :: 3
License-File: LICENSE
Requires-Dist: jsonschema
